marscode_baas_sdk/__init__.py
marscode_baas_sdk/file.py
marscode_baas_sdk/redis.py
marscode_baas_sdk/remote/__init__.py
marscode_baas_sdk/remote/auth.py
marscode_baas_sdk/remote/config.py
marscode_baas_sdk/remote/const.py
marscode_baas_sdk/remote/file_api.py
marscode_baas_sdk/remote/redis_api.py
marscode_baas_sdk/remote/utils.py
marscode_baas_sdk-0.1.0.dist-info/LICENSE
marscode_baas_sdk-0.1.0.dist-info/METADATA
marscode_baas_sdk-0.1.0.dist-info/NOTICE
marscode_baas_sdk-0.1.0.dist-info/WHEEL
marscode_baas_sdk-0.1.0.dist-info/top_level.txt
marscode_baas_sdk-0.1.0.dist-info/RECORD
