Metadata-Version: 2.1
Name: marscode_baas_sdk
Version: 0.1.0
Summary: baas sdk for marscode project
Author: marscode
License: MIT
Requires-Python: >=3.8
License-File: LICENSE
License-File: NOTICE
Requires-Dist: requests >=2.31.0
Requires-Dist: urllib3 >=2.1.0
